Jenkinsfile
MANIFEST.in
Makefile
README.md
build.parameters
hassmpris.spec
mypy.ini
pyproject.toml
setup.cfg
tox.ini
src/hassmpris/__init__.py
src/hassmpris/certs.py
src/hassmpris/config.py
src/hassmpris/py.typed
src/hassmpris.egg-info/PKG-INFO
src/hassmpris.egg-info/SOURCES.txt
src/hassmpris.egg-info/dependency_links.txt
src/hassmpris.egg-info/requires.txt
src/hassmpris.egg-info/top_level.txt
src/hassmpris/proto/__init__.py
src/hassmpris/proto/mpris_grpc.py
src/hassmpris/proto/mpris_pb2.py
src/hassmpris/proto/mpris_pb2_grpc.py
tests/conftest.py
tests/test_dummy.py