Metadata-Version: 2.1
Name: hassmpris
Version: 0.1.10
Summary: Linux desktop multimedia integration with Home Assistant
Home-page: https://github.com/Rudd-O/hassmpris
Author: Manuel Amador (Rudd-O)
Author-email: rudd-o@rudd-o.com
Classifier: Programming Language :: Python :: 3
Classifier: License :: OSI Approved :: GNU Lesser General Public License v2 (LGPLv2)
